py_obfuscate/__init__.py
py_obfuscate/insertstatement.py
py_obfuscate/mysql.py
py_obfuscate/py_obfuscator.py
py_obfuscate/test_mysql.py
py_obfuscate/test_py_obfuscator.py
py_obfuscate/test_py_obfuscator_insert.py
py_obfuscate-0.1.6.dist-info/LICENSE.txt
py_obfuscate-0.1.6.dist-info/METADATA
py_obfuscate-0.1.6.dist-info/WHEEL
py_obfuscate-0.1.6.dist-info/top_level.txt
py_obfuscate-0.1.6.dist-info/RECORD
