Metadata-Version: 2.1
Name: py-obfuscate
Version: 0.1.6
Summary: A module for obfuscating a mysqldump file
Home-page: https://github.com/stephenharris/py_obfuscate
Author: Stephen Harris
License: UNKNOWN
Keywords: obfuscate mysqldump mysql
Platform: UNKNOWN
Classifier: Development Status :: 4 - Beta
Classifier: Intended Audience :: Developers
Classifier: Topic :: Software Development :: Libraries :: Python Modules
Classifier: Topic :: Text Processing
Classifier: License :: OSI Approved :: MIT License
Classifier: Programming Language :: Python :: 3.6
Classifier: Programming Language :: Python :: 3.7
Requires-Dist: faker
